{
  "System": {
    "BasePath": "/exe",
    "JQPath":"/opt/jq",
    "Port": 8999,
    "ScriptsPath": "/opt/script",
    "LOGPATH": "/srv/vxlog",
    "RegExRule": "(.*?)",
    "CBHOST": "10.12.1.221",
    "CBPROTO": "http",
    "CBPORT": "8085",
    "CBPATH": "cb",
    "LBURL": "http://localhost:8999/lb",

    "debug":true,
    "eb" : {
	"bridge":{
		"inbound":  [{ "address":"executions" },{ "address":"node" }],
		"outbound": [{ "address":"executions" },{ "address":"node" }]
		}
	}

  },
  "SSH": {
    "cmd": "/opt/script/crshcmd",
    "crash.auth": "simple",
    "crash.auth.simple.username": "admin",
    "crash.auth.simple.password": "admin",
    "crash.ssh.port": 2222
   }
}

